textslack/__init__.py
textslack/textslack.py
textslack-0.1.5.dist-info/LICENSE
textslack-0.1.5.dist-info/METADATA
textslack-0.1.5.dist-info/WHEEL
textslack-0.1.5.dist-info/top_level.txt
textslack-0.1.5.dist-info/RECORD
