Metadata-Version: 2.1
Name: textslack
Version: 0.1.5
Summary: Play with text data
Home-page: https://github.com/AnkitRajSri/textslack.git
Author: Ankit Raj
Author-email: srivastavaankit667@gmail.com
License: MIT
Platform: UNKNOWN
Classifier: License :: OSI Approved :: MIT License
Classifier: Programming Language :: Python
Classifier: Programming Language :: Python :: 3.5
Classifier: Programming Language :: Python :: 3.6
Classifier: Programming Language :: Python :: 3.7
Classifier: Topic :: Software Development :: Libraries
Classifier: Topic :: Software Development :: Libraries :: Python Modules
Requires-Dist: pandas
Requires-Dist: nltk
Requires-Dist: textblob
Requires-Dist: sklearn
Requires-Dist: normalise
